setup.py
tsmc/__init__.py
tsmc.egg-info/PKG-INFO
tsmc.egg-info/SOURCES.txt
tsmc.egg-info/dependency_links.txt
tsmc.egg-info/top_level.txt