Metadata-Version: 2.1
Name: tsmc
Version: 0.0.1
Summary: Cool Package
Author: Intel#1563
